tests/__init__.py
tests/test_w3u.py
w3u/__init__.py
w3u_THEGISMAR-0.0.1.dist-info/METADATA
w3u_THEGISMAR-0.0.1.dist-info/WHEEL
w3u_THEGISMAR-0.0.1.dist-info/top_level.txt
w3u_THEGISMAR-0.0.1.dist-info/RECORD
