Metadata-Version: 2.1
Name: w3u-THEGISMAR
Version: 0.0.1
Summary: Some convenience functions to make web3 coding easier.
Home-page: https://github.com/thegismar/w3u
Author: thegismar
License: UNKNOWN
Platform: UNKNOWN
Requires-Python: >=3.6
